msys/__init__.py
msys/registration.py
msys/core/__init__.py
msys/core/connectable.py
msys/core/connection.py
msys/core/interfaces.py
msys/core/metadata.py
msys/core/module.py
msys/core/option.py
msys/core/registrable.py
msys/core/serializer.py
msys/core/serializer_collections.py
msys/core/type.py
msys/core/unit.py
msys/modules/__init__.py
msys/modules/network.py
msys/scripts/__init__.py
msys/scripts/msys.py
msys/server/__init__.py
msys/server/api.py
msys/types/__init__.py
msys/types/file.py
msys-0.2.5.dist-info/LICENSE
msys-0.2.5.dist-info/METADATA
msys-0.2.5.dist-info/WHEEL
msys-0.2.5.dist-info/entry_points.txt
msys-0.2.5.dist-info/top_level.txt
msys-0.2.5.dist-info/RECORD
